piku/__init__.py
piku/commands/__init__.py
piku/commands/add.py
piku/commands/create.py
piku/commands/deploy.py
piku/commands/info.py
piku/commands/install.py
piku/commands/remove.py
piku/commands/serial.py
piku/commands/upgrade.py
piku/commands/version.py
piku/core/config.py
piku/core/device.py
piku/core/errors.py
piku/core/locker.py
piku/core/packages.py
piku/core/utils/__init__.py
piku/core/utils/cache.py
piku/core/utils/sync.py
piku/core/utils/utils.py
piku/core/utils/watcher.py
piku/main.py
piku/template/.gitignore
piku/template/README.md
piku/template/project/code.py
piku/template/pyproject.toml
piku-0.2.4.dist-info/entry_points.txt
piku-0.2.4.dist-info/LICENSE
piku-0.2.4.dist-info/WHEEL
piku-0.2.4.dist-info/METADATA
piku-0.2.4.dist-info/RECORD
