Metadata-Version: 2.1
Name: piku
Version: 0.2.4
Summary: 
Home-page: https://github.com/mraleson/piku.git
License: MIT
Author: Mark Raleson
Author-email: markraleson@outlook.com
Requires-Python: >=3.8,<4.0
Classifier: License :: OSI Approved :: MIT License
Classifier: Programming Language :: Python :: 3
Classifier: Programming Language :: Python :: 3.8
Classifier: Programming Language :: Python :: 3.9
Classifier: Programming Language :: Python :: 3.10
Classifier: Programming Language :: Python :: 3.11
Requires-Dist: Jinja2 (>=3.0.3,<4.0.0)
Requires-Dist: adafruit-board-toolkit (>=1.1.0,<2.0.0)
Requires-Dist: appdirs (>=1.4.4,<2.0.0)
Requires-Dist: cachy (>=0.3.0,<0.4.0)
Requires-Dist: poetry-core (==1.0.7)
Requires-Dist: pyserial (>=3.5,<4.0)
Requires-Dist: requests (>=2.27.1,<3.0.0)
Requires-Dist: toml (>=0.10.2,<0.11.0)
Requires-Dist: watchdog (>=2.1.7,<3.0.0)
Project-URL: Repository, https://github.com/mraleson/piku.git
